{
  "aggregate": {
    "timestamp": "2021-04-04T02:58:58.342Z",
    "scenariosCreated": 1000,
    "scenariosCompleted": 1000,
    "requestsCompleted": 1000,
    "latency": {
      "min": 46.4,
      "max": 60.5,
      "median": 55.7,
      "p95": 57.8,
      "p99": 59.5
    },
    "rps": {
      "count": 1000,
      "mean": 9.96
    },
    "scenarioDuration": {
      "min": 48,
      "max": 85.8,
      "median": 57.4,
      "p95": 60,
      "p99": 61.7
    },
    "scenarioCounts": {
      "0": 1000
    },
    "errors": {},
    "codes": {
      "200": 1000
    },
    "matches": 0,
    "customStats": {},
    "counters": {},
    "scenariosAvoided": 0,
    "phases": [
      {
        "duration": 100,
        "arrivalRate": 10
      }
    ]
  },
  "intermediate": [
    {
      "timestamp": "2021-04-04T02:57:27.823Z",
      "scenariosCreated": 99,
      "scenariosCompleted": 99,
      "requestsCompleted": 99,
      "latency": {
        "min": 51.1,
        "max": 59.3,
        "median": 55.5,
        "p95": 57.2,
        "p99": 59.1
      },
      "rps": {
        "count": 99,
        "mean": 10.03
      },
      "scenarioDuration": {
        "min": 54.7,
        "max": 85.8,
        "median": 57.5,
        "p95": 59.6,
        "p99": 73.6
      },
      "scenarioCounts": {
        "0": 99
      },
      "errors": {},
      "codes": {
        "200": 99
      },
      "matches": 0,
      "latencies": [
        55423784,
        51145142,
        55636051,
        54219894,
        55349182,
        56224640,
        57041193,
        56579478,
        54971728,
        54704605,
        55891162,
        55386104,
        54277224,
        56980303,
        56038954,
        56458796,
        55651134,
        56184449,
        56315730,
        55062321,
        54722949,
        55986873,
        54756068,
        54319549,
        54226637,
        56186855,
        55954321,
        57156119,
        53321063,
        58914814,
        56225521,
        55979638,
        54276979,
        54452172,
        56165782,
        54617616,
        54284986,
        54235600,
        54913126,
        55554871,
        55713074,
        55927721,
        55669164,
        55458807,
        57167067,
        55524014,
        56163448,
        55527520,
        54325097,
        54986453,
        55630596,
        54054930,
        56925494,
        55183553,
        57375506,
        55982390,
        55061084,
        55050163,
        56810829,
        55675362,
        54396873,
        55934478,
        56520635,
        55084296,
        55670630,
        56125532,
        56973095,
        56201713,
        54977098,
        55342389,
        54916632,
        59313466,
        55678123,
        54947659,
        55690482,
        55521882,
        56132923,
        54031068,
        56325120,
        53729890,
        55236996,
        55162995,
        56828655,
        54541002,
        54105988,
        54850514,
        54837331,
        56520371,
        56285461,
        54016508,
        55101793,
        55040975,
        54894395,
        56005726,
        57163035,
        55470242,
        55498257,
        54840858,
        55135235
      ],
      "customStats": {},
      "counters": {},
      "concurrency": 0,
      "pendingRequests": 0,
      "scenariosAvoided": 0
    },
    {
      "timestamp": "2021-04-04T02:57:37.821Z",
      "scenariosCreated": 100,
      "scenariosCompleted": 100,
      "requestsCompleted": 100,
      "latency": {
        "min": 46.4,
        "max": 60.5,
        "median": 55.3,
        "p95": 57.4,
        "p99": 60
      },
      "rps": {
        "count": 100,
        "mean": 10.01
      },
      "scenarioDuration": {
        "min": 48,
        "max": 62.7,
        "median": 57.1,
        "p95": 60.2,
        "p99": 62.5
      },
      "scenarioCounts": {
        "0": 100
      },
      "errors": {},
      "codes": {
        "200": 100
      },
      "matches": 0,
      "latencies": [
        55075285,
        55736005,
        53995523,
        55954631,
        55229741,
        55991146,
        56045943,
        55733295,
        55913914,
        55582686,
        54592913,
        53714128,
        55679474,
        55673967,
        55333817,
        57632599,
        54412914,
        55033009,
        54817647,
        55170143,
        56587293,
        54461497,
        54971081,
        57295303,
        55817147,
        55176708,
        54248716,
        55226271,
        56533077,
        55859572,
        55174289,
        55068451,
        54749821,
        55041293,
        54724134,
        53609192,
        55711974,
        56098992,
        54961084,
        56027788,
        54667772,
        54893262,
        56690417,
        55338606,
        60511855,
        54877951,
        54645760,
        54791314,
        55339304,
        56213080,
        55201085,
        55239128,
        55225431,
        54558545,
        57458896,
        55635882,
        54491659,
        57201595,
        55098300,
        54660277,
        55585939,
        54835628,
        56583383,
        54370856,
        46366471,
        55526243,
        55646981,
        55455143,
        54427535,
        57412862,
        54380946,
        55470150,
        55578631,
        57149842,
        54388041,
        56223703,
        54536075,
        57201584,
        55439013,
        54382498,
        54488525,
        55075820,
        56974060,
        55256010,
        59512491,
        55926757,
        55626052,
        55889469,
        55030355,
        55125946,
        55139877,
        54477816,
        55611992,
        54621980,
        55419514,
        54355858,
        56356992,
        55565555,
        56094542,
        55663799
      ],
      "customStats": {},
      "counters": {},
      "concurrency": 0,
      "pendingRequests": 0,
      "scenariosAvoided": 0
    },
    {
      "timestamp": "2021-04-04T02:57:47.821Z",
      "scenariosCreated": 100,
      "scenariosCompleted": 100,
      "requestsCompleted": 100,
      "latency": {
        "min": 53,
        "max": 59.5,
        "median": 55.5,
        "p95": 57.2,
        "p99": 58.9
      },
      "rps": {
        "count": 100,
        "mean": 10
      },
      "scenarioDuration": {
        "min": 54.6,
        "max": 62.1,
        "median": 57.4,
        "p95": 60.2,
        "p99": 61.7
      },
      "scenarioCounts": {
        "0": 100
      },
      "errors": {},
      "codes": {
        "200": 100
      },
      "matches": 0,
      "latencies": [
        57627155,
        54956037,
        54187200,
        52972911,
        55523114,
        55174127,
        54760751,
        56439439,
        54360296,
        56328500,
        55039854,
        55506354,
        59544226,
        56222603,
        56318645,
        56531700,
        55567485,
        56159042,
        54859593,
        56111764,
        54328866,
        56417488,
        55406490,
        55720051,
        54881673,
        55561389,
        54890584,
        56149376,
        54641040,
        55547033,
        55291440,
        55945875,
        55038054,
        56613060,
        55839914,
        55319665,
        54159980,
        54955244,
        55164808,
        55487264,
        56361617,
        54892860,
        54660388,
        54740008,
        55422763,
        55420860,
        54943488,
        55645300,
        55956156,
        55527775,
        57304173,
        55256137,
        57606818,
        55150304,
        55256062,
        54612650,
        55248358,
        54573124,
        54331231,
        55717336,
        55539566,
        56283233,
        54056789,
        55685840,
        55900163,
        56820955,
        57057985,
        56849426,
        55912129,
        54639141,
        54664203,
        55850285,
        54786301,
        56109752,
        55556233,
        54672835,
        55016263,
        56408076,
        56286331,
        55875590,
        54355017,
        55678289,
        56206742,
        55973485,
        55666027,
        53828422,
        54052074,
        56809933,
        54685493,
        55019404,
        56031618,
        55408826,
        58271052,
        54882246,
        56315711,
        55039342,
        54728875,
        55258531,
        55756323,
        56501046
      ],
      "customStats": {},
      "counters": {},
      "concurrency": 0,
      "pendingRequests": 0,
      "scenariosAvoided": 0
    },
    {
      "timestamp": "2021-04-04T02:57:57.821Z",
      "scenariosCreated": 100,
      "scenariosCompleted": 100,
      "requestsCompleted": 100,
      "latency": {
        "min": 53.6,
        "max": 59.8,
        "median": 55.5,
        "p95": 57.8,
        "p99": 59.4
      },
      "rps": {
        "count": 100,
        "mean": 10
      },
      "scenarioDuration": {
        "min": 55.4,
        "max": 61.7,
        "median": 57.3,
        "p95": 59.8,
        "p99": 61.2
      },
      "scenarioCounts": {
        "0": 100
      },
      "errors": {},
      "codes": {
        "200": 100
      },
      "matches": 0,
      "latencies": [
        57985409,
        57879703,
        54902730,
        55924580,
        55331249,
        55779827,
        55650660,
        55007884,
        55995950,
        55585312,
        55353209,
        54759978,
        55440763,
        56669580,
        55303941,
        56564312,
        55387437,
        55838890,
        55272048,
        54554671,
        55050110,
        56071227,
        55017620,
        55757753,
        56072210,
        58097522,
        54426448,
        56468487,
        54830051,
        57180851,
        53637755,
        57291699,
        55591717,
        54931323,
        55411568,
        55471046,
        56765050,
        55999652,
        55798090,
        55448585,
        54639695,
        55827846,
        55486751,
        55735283,
        56836360,
        55856106,
        54529763,
        56698317,
        54902746,
        55998325,
        59060805,
        54612081,
        56076218,
        54534807,
        54013642,
        54891084,
        56786822,
        54670012,
        54970797,
        55882463,
        54922998,
        54637226,
        56123044,
        55122958,
        54324923,
        54871602,
        56347247,
        55882218,
        55539654,
        57034632,
        55095944,
        56796250,
        54849248,
        55483033,
        55125173,
        59774969,
        55558538,
        55667260,
        55073513,
        56404052,
        55466329,
        54762257,
        57122493,
        54758667,
        56351159,
        54632816,
        54618179,
        55799946,
        55650843,
        56552862,
        56095616,
        54662275,
        54758797,
        54245932,
        57111690,
        57735924,
        54688127,
        53943306,
        54823943,
        56240746
      ],
      "customStats": {},
      "counters": {},
      "concurrency": 0,
      "pendingRequests": 0,
      "scenariosAvoided": 0
    },
    {
      "timestamp": "2021-04-04T02:58:07.821Z",
      "scenariosCreated": 100,
      "scenariosCompleted": 100,
      "requestsCompleted": 100,
      "latency": {
        "min": 53.5,
        "max": 59,
        "median": 55.5,
        "p95": 57.8,
        "p99": 58.8
      },
      "rps": {
        "count": 100,
        "mean": 10
      },
      "scenarioDuration": {
        "min": 54.7,
        "max": 63.6,
        "median": 57.3,
        "p95": 60.2,
        "p99": 62.1
      },
      "scenarioCounts": {
        "0": 100
      },
      "errors": {},
      "codes": {
        "200": 100
      },
      "matches": 0,
      "latencies": [
        59005156,
        53814087,
        54810449,
        57174485,
        54008792,
        54603085,
        55759122,
        57644715,
        55441525,
        54696780,
        56248702,
        55819485,
        55984137,
        56883948,
        56831945,
        56678465,
        55483933,
        56309419,
        55090625,
        55372592,
        57460903,
        54476011,
        53758663,
        55881978,
        54504101,
        56480554,
        54907505,
        54708734,
        56661357,
        55583587,
        55313207,
        55764037,
        55744352,
        54993931,
        56494267,
        54661340,
        54619012,
        54892681,
        56298692,
        55708651,
        55950460,
        55187037,
        55548986,
        55170840,
        54597613,
        55265349,
        56300451,
        58055550,
        55934194,
        54780676,
        58605727,
        55423575,
        57863916,
        55349583,
        54892898,
        55799810,
        54619607,
        55920520,
        55558315,
        55127576,
        55092625,
        55734865,
        53913290,
        56660326,
        56586368,
        53480890,
        57126292,
        54380646,
        56127939,
        55616853,
        55120377,
        55942068,
        55692308,
        55237064,
        54418285,
        57865808,
        54762825,
        55386359,
        56944992,
        55975124,
        54939309,
        55320862,
        54720641,
        55256990,
        55754345,
        56654943,
        55103320,
        54474406,
        57633174,
        56115821,
        55612837,
        54986461,
        55885579,
        55364058,
        55939067,
        55246591,
        54427059,
        56298213,
        54231423,
        55035265
      ],
      "customStats": {},
      "counters": {},
      "concurrency": 0,
      "pendingRequests": 0,
      "scenariosAvoided": 0
    },
    {
      "timestamp": "2021-04-04T02:58:17.822Z",
      "scenariosCreated": 100,
      "scenariosCompleted": 100,
      "requestsCompleted": 100,
      "latency": {
        "min": 53.3,
        "max": 59.6,
        "median": 55.6,
        "p95": 58.7,
        "p99": 59.6
      },
      "rps": {
        "count": 100,
        "mean": 10
      },
      "scenarioDuration": {
        "min": 55.6,
        "max": 61.5,
        "median": 57.4,
        "p95": 60.6,
        "p99": 61.4
      },
      "scenarioCounts": {
        "0": 100
      },
      "errors": {},
      "codes": {
        "200": 100
      },
      "matches": 0,
      "latencies": [
        59646434,
        56274400,
        54933818,
        56686748,
        55942252,
        55206807,
        55847569,
        55448872,
        57733086,
        55803007,
        55423655,
        55672645,
        56813788,
        56389888,
        55357815,
        55757878,
        56111794,
        55180160,
        54770556,
        56002338,
        57511946,
        56455143,
        54604624,
        54787099,
        55153047,
        58930320,
        55653222,
        54767539,
        56465595,
        55225294,
        55131880,
        54851979,
        56536234,
        56253305,
        54522633,
        54487641,
        56005304,
        56660834,
        56616414,
        58723397,
        54822742,
        55473218,
        55063862,
        56141384,
        55666774,
        56423563,
        56119198,
        56829108,
        54333722,
        55090178,
        58739331,
        55153196,
        59567799,
        55433777,
        56632761,
        54850229,
        55808046,
        56215184,
        55951117,
        55160928,
        56839607,
        55720878,
        55210740,
        56992588,
        55176622,
        55529627,
        56925939,
        54984278,
        54890343,
        55258510,
        54223776,
        55602247,
        57289995,
        56067021,
        53418164,
        58927137,
        54870666,
        55969220,
        56133929,
        55297107,
        55993148,
        54590352,
        56434908,
        54768411,
        55148135,
        58050530,
        54171324,
        53283326,
        54944942,
        54721591,
        55454517,
        56317127,
        55943309,
        54920219,
        55266437,
        55835943,
        54711455,
        55194476,
        54119041,
        54346032
      ],
      "customStats": {},
      "counters": {},
      "concurrency": 0,
      "pendingRequests": 0,
      "scenariosAvoided": 0
    },
    {
      "timestamp": "2021-04-04T02:58:27.822Z",
      "scenariosCreated": 100,
      "scenariosCompleted": 100,
      "requestsCompleted": 100,
      "latency": {
        "min": 53.5,
        "max": 59.6,
        "median": 55.5,
        "p95": 57.9,
        "p99": 59.1
      },
      "rps": {
        "count": 100,
        "mean": 10
      },
      "scenarioDuration": {
        "min": 55.1,
        "max": 61.2,
        "median": 57.2,
        "p95": 59.9,
        "p99": 60.9
      },
      "scenarioCounts": {
        "0": 100
      },
      "errors": {},
      "codes": {
        "200": 100
      },
      "matches": 0,
      "latencies": [
        59604018,
        54596746,
        55765906,
        56803609,
        55212603,
        57907474,
        56138387,
        55262095,
        54605063,
        54397023,
        55071609,
        55570407,
        55203473,
        56007931,
        56369788,
        56400997,
        55595030,
        55991290,
        53961411,
        56246551,
        54736946,
        55977271,
        53510601,
        55523744,
        54800328,
        57559023,
        55084121,
        55719064,
        54705406,
        55316350,
        54839112,
        58561855,
        54495751,
        56384687,
        57467737,
        55361316,
        56290556,
        53907267,
        54463388,
        54393390,
        55234922,
        56252371,
        55163431,
        56371744,
        55247183,
        55775377,
        55749657,
        54901773,
        55673372,
        54222029,
        58035347,
        54500767,
        56648554,
        55628138,
        54531402,
        55547566,
        53920163,
        57098371,
        56335969,
        54370500,
        54702280,
        55550581,
        55495321,
        55743676,
        55035120,
        53786696,
        55896263,
        54684189,
        54789684,
        53566633,
        56256399,
        54717335,
        57274118,
        55913283,
        54906407,
        58381397,
        55517541,
        54777802,
        56400008,
        54496963,
        55533461,
        54592026,
        56929987,
        56429906,
        54971926,
        56514378,
        54856056,
        56828663,
        53593132,
        55444090,
        56279050,
        57409873,
        55435643,
        54633253,
        55414994,
        55487165,
        55261969,
        57101918,
        55126655,
        57826353
      ],
      "customStats": {},
      "counters": {},
      "concurrency": 0,
      "pendingRequests": 0,
      "scenariosAvoided": 0
    },
    {
      "timestamp": "2021-04-04T02:58:37.823Z",
      "scenariosCreated": 100,
      "scenariosCompleted": 100,
      "requestsCompleted": 100,
      "latency": {
        "min": 53.7,
        "max": 59.6,
        "median": 55.8,
        "p95": 58.4,
        "p99": 59.4
      },
      "rps": {
        "count": 100,
        "mean": 10
      },
      "scenarioDuration": {
        "min": 55.3,
        "max": 61.2,
        "median": 57.5,
        "p95": 60,
        "p99": 61
      },
      "scenarioCounts": {
        "0": 100
      },
      "errors": {},
      "codes": {
        "200": 100
      },
      "matches": 0,
      "latencies": [
        58721157,
        54827873,
        56481621,
        55630506,
        56080775,
        55748271,
        55945359,
        55357701,
        55819095,
        54099926,
        54671450,
        54900758,
        56486367,
        56255696,
        55468958,
        55040374,
        55903596,
        54531817,
        56902071,
        55940717,
        55511094,
        54895111,
        55925508,
        55913358,
        55812964,
        59225936,
        55201041,
        55734656,
        55549886,
        55574699,
        57092548,
        56634721,
        59126527,
        55836827,
        54127485,
        55275073,
        55310705,
        53691238,
        55357218,
        54296999,
        56042747,
        55832677,
        55523699,
        55186752,
        56376641,
        55937048,
        56639093,
        54532203,
        54070790,
        57614626,
        58149335,
        54795970,
        55186701,
        56800231,
        55526316,
        57143905,
        54427933,
        56287527,
        55756409,
        55381738,
        56547912,
        59588088,
        55635791,
        54562257,
        55679705,
        55933853,
        54579443,
        55876589,
        55933342,
        55574460,
        55441868,
        55972876,
        56718063,
        57027278,
        55327757,
        58411843,
        56587863,
        55922885,
        55901425,
        55981312,
        57580946,
        55935998,
        56745164,
        57099475,
        58357014,
        57144975,
        55731150,
        56279199,
        55662646,
        54933548,
        55419207,
        55666193,
        56367047,
        56868415,
        54841584,
        55043468,
        55345503,
        55475063,
        56643393,
        54775645
      ],
      "customStats": {},
      "counters": {},
      "concurrency": 0,
      "pendingRequests": 0,
      "scenariosAvoided": 0
    },
    {
      "timestamp": "2021-04-04T02:58:47.822Z",
      "scenariosCreated": 100,
      "scenariosCompleted": 100,
      "requestsCompleted": 100,
      "latency": {
        "min": 54.1,
        "max": 60,
        "median": 56,
        "p95": 57.9,
        "p99": 59.6
      },
      "rps": {
        "count": 100,
        "mean": 10
      },
      "scenarioDuration": {
        "min": 55.7,
        "max": 61.6,
        "median": 58,
        "p95": 59.7,
        "p99": 61.3
      },
      "scenarioCounts": {
        "0": 100
      },
      "errors": {},
      "codes": {
        "200": 100
      },
      "matches": 0,
      "latencies": [
        59190471,
        56565529,
        55400396,
        55121848,
        55465668,
        55617601,
        55515250,
        55891182,
        56843483,
        56439755,
        54585276,
        55862269,
        56591350,
        55965092,
        56121885,
        57621838,
        54830518,
        57614170,
        55534051,
        55689183,
        55619778,
        55594301,
        55871678,
        56890925,
        54516251,
        57238291,
        55348225,
        57007531,
        55060722,
        54775456,
        55575408,
        57089723,
        55240548,
        56787032,
        55800216,
        55491732,
        55458171,
        55988697,
        56404232,
        57103677,
        55838118,
        56099816,
        55317355,
        57781093,
        55678684,
        56179488,
        55652841,
        55256633,
        55901108,
        56823629,
        58188936,
        56632955,
        55887983,
        55854564,
        56448011,
        56137091,
        57368141,
        55580009,
        56389368,
        57937977,
        55561324,
        55378780,
        55978224,
        57788276,
        57048201,
        57371911,
        56556711,
        57230741,
        56198022,
        56908502,
        55665762,
        57575440,
        56249357,
        55382387,
        56872733,
        60016363,
        56528538,
        58305655,
        54733564,
        57564459,
        54107998,
        55265287,
        55659424,
        56789448,
        56132163,
        57651191,
        56213301,
        57212368,
        55370073,
        56560209,
        55830869,
        55785405,
        57074275,
        55048180,
        57396039,
        55926541,
        55266918,
        56634607,
        55805757,
        57163498
      ],
      "customStats": {},
      "counters": {},
      "concurrency": 0,
      "pendingRequests": 0,
      "scenariosAvoided": 0
    },
    {
      "timestamp": "2021-04-04T02:58:57.824Z",
      "scenariosCreated": 100,
      "scenariosCompleted": 100,
      "requestsCompleted": 100,
      "latency": {
        "min": 53.6,
        "max": 60.5,
        "median": 56.3,
        "p95": 58.4,
        "p99": 60.4
      },
      "rps": {
        "count": 100,
        "mean": 10
      },
      "scenarioDuration": {
        "min": 55.1,
        "max": 62.2,
        "median": 58.1,
        "p95": 60.7,
        "p99": 62
      },
      "scenarioCounts": {
        "0": 100
      },
      "errors": {},
      "codes": {
        "200": 100
      },
      "matches": 0,
      "latencies": [
        60221064,
        56847692,
        55647279,
        55275921,
        56791092,
        55176609,
        56144932,
        56945157,
        55444825,
        57363232,
        56182601,
        56249881,
        57476281,
        56090689,
        56569260,
        56362616,
        55047479,
        56476181,
        55322246,
        57719472,
        58221392,
        55579766,
        56293084,
        56573977,
        56578405,
        58181810,
        55880661,
        56011363,
        55435168,
        55130464,
        60523075,
        56452998,
        59310170,
        56883202,
        56247380,
        57926274,
        57239147,
        55471612,
        56538073,
        56455513,
        56255620,
        56753242,
        56465555,
        56618423,
        56742746,
        55500483,
        55445518,
        56329228,
        55784828,
        54163656,
        58796520,
        56457475,
        55837819,
        54559349,
        55951147,
        55789968,
        55113565,
        56609701,
        56074924,
        54738572,
        55428579,
        56866824,
        57707294,
        56197629,
        57145680,
        55483803,
        55467754,
        55750276,
        55998828,
        56224009,
        55737696,
        55214786,
        55835350,
        55239439,
        56914230,
        55620738,
        55741225,
        56681058,
        57800319,
        56583545,
        57259251,
        58559023,
        56814530,
        56262359,
        56219533,
        56250686,
        56519581,
        56522368,
        55433705,
        54722496,
        57550455,
        57477940,
        55724992,
        56162941,
        55628676,
        55923307,
        56168303,
        56574846,
        56282816,
        53581835
      ],
      "customStats": {},
      "counters": {},
      "concurrency": 0,
      "pendingRequests": 0,
      "scenariosAvoided": 0
    },
    {
      "timestamp": "2021-04-04T02:58:58.332Z",
      "scenariosCreated": 1,
      "scenariosCompleted": 1,
      "requestsCompleted": 1,
      "latency": {
        "min": 56.1,
        "max": 56.1,
        "median": 56.1,
        "p95": 56.1,
        "p99": 56.1
      },
      "rps": {
        "count": 1,
        "mean": 2
      },
      "scenarioDuration": {
        "min": 63,
        "max": 63,
        "median": 63,
        "p95": 63,
        "p99": 63
      },
      "scenarioCounts": {
        "0": 1
      },
      "errors": {},
      "codes": {
        "200": 1
      },
      "matches": 0,
      "latencies": [
        56113457
      ],
      "customStats": {},
      "counters": {},
      "concurrency": 0,
      "pendingRequests": 0,
      "scenariosAvoided": 0
    }
  ]
}